binarytreepy/__init__.py
binarytreepy/tree.py
binarytreepy-0.0.1.dist-info/METADATA
binarytreepy-0.0.1.dist-info/WHEEL
binarytreepy-0.0.1.dist-info/top_level.txt
binarytreepy-0.0.1.dist-info/RECORD
